pi_compute/__init__.py
pi_compute/pi.py
pi_compute/include/pi.cpp
pi_compute/lib/lib_pi.so
pi_compute-3.14.15.dist-info/LICENSE
pi_compute-3.14.15.dist-info/METADATA
pi_compute-3.14.15.dist-info/WHEEL
pi_compute-3.14.15.dist-info/top_level.txt
pi_compute-3.14.15.dist-info/RECORD
