Metadata-Version: 2.1
Name: pi-compute
Version: 3.14.15
Summary: to compute N digits of pi
Home-page: https://github.com/tlming16/pi
Author: mathm
Author-email: tlming16@fudan.edu.cn
License: UNKNOWN
Project-URL: Bug Tracker, https://github.com/tlming16/pi-/issues
Platform: UNKNOWN
Classifier: Programming Language :: Python :: 3
Classifier: License :: OSI Approved :: MIT License
Classifier: Operating System :: OS Independent
Requires-Python: >=3.6
License-File: LICENSE
